[
    {
        "tribe": "igbo",
        "gender": "female",
        "name": "Chinwe"
    },
    {
        "tribe": "igbo",
        "gender": "female",
        "name": "Ngozi"
    },
    {
        "tribe": "igbo",
        "gender": "female",
        "name": "Uche"
    },
    {
        "tribe": "igbo",
        "gender": "female",
        "name": "Chioma"
    },
    {
        "tribe": "igbo",
        "gender": "female",
        "name": "Chiamaka"
    },
    {
        "tribe": "igbo",
        "gender": "female",
        "name": "Adaeze"
    },
    {
        "tribe": "igbo",
        "gender": "female",
        "name": "Ifeoma"
    },
    {
        "tribe": "igbo",
        "gender": "female",
        "name": "Obianuju"
    },
    {
        "tribe": "igbo",
        "gender": "female",
        "name": "Chizoba"
    },
    {
        "tribe": "igbo",
        "gender": "female",
        "name": "Chidimma"
    },
    {
        "tribe": "igbo",
        "gender": "female",
        "name": "Nneka"
    },
    {
        "tribe": "igbo",
        "gender": "female",
        "name": "Oluchi"
    },
    {
        "tribe": "igbo",
        "gender": "female",
        "name": "Ginika"
    },
    {
        "tribe": "igbo",
        "gender": "female",
        "name": "Uju"
    },
    {
        "tribe": "igbo",
        "gender": "female",
        "name": "Ogechi"
    },
    {
        "tribe": "igbo",
        "gender": "female",
        "name": "Chisom"
    },
    {
        "tribe": "igbo",
        "gender": "female",
        "name": "Ifunanya"
    },
    {
        "tribe": "igbo",
        "gender": "female",
        "name": "Kamsiyochukwu"
    },
    {
        "tribe": "igbo",
        "gender": "female",
        "name": "Nwakaego"
    },
    {
        "tribe": "igbo",
        "gender": "female",
        "name": "Chinyere"
    },
    {
        "tribe": "igbo",
        "gender": "female",
        "name": "Kosisochukwu"
    },
    {
        "tribe": "igbo",
        "gender": "female",
        "name": "Chiwendu"
    },
    {
        "tribe": "igbo",
        "gender": "female",
        "name": "Obiageli"
    },
    {
        "tribe": "igbo",
        "gender": "female",
        "name": "Nkemdirim"
    }
]
