[
    {
        "ethnic_group": "hausa",
        "gender": "female",
        "name": "Fatima"
    },
    {
        "ethnic_group": "hausa",
        "gender": "female",
        "name": "Aisha"
    },
    {
        "ethnic_group": "hausa",
        "gender": "female",
        "name": "Zainab"
    },
    {
        "ethnic_group": "hausa",
        "gender": "female",
        "name": "Hauwa"
    },
    {
        "ethnic_group": "hausa",
        "gender": "female",
        "name": "Maryam"
    },
    {
        "ethnic_group": "hausa",
        "gender": "female",
        "name": "Halima"
    },
    {
        "ethnic_group": "hausa",
        "gender": "female",
        "name": "Zahra"
    },
    {
        "ethnic_group": "hausa",
        "gender": "female",
        "name": "Amina"
    },
    {
        "ethnic_group": "hausa",
        "gender": "female",
        "name": "Rabi"
    },
    {
        "ethnic_group": "hausa",
        "gender": "female",
        "name": "Aisha"
    },
    {
        "ethnic_group": "hausa",
        "gender": "female",
        "name": "Nana"
    },
    {
        "ethnic_group": "hausa",
        "gender": "female",
        "name": "Falmata"
    },
    {
        "ethnic_group": "hausa",
        "gender": "female",
        "name": "Asmau"
    },
    {
        "ethnic_group": "hausa",
        "gender": "female",
        "name": "Rahama"
    },
    {
        "ethnic_group": "hausa",
        "gender": "female",
        "name": "Sadiya"
    },
    {
        "ethnic_group": "hausa",
        "gender": "female",
        "name": "Amina"
    },
    {
        "ethnic_group": "hausa",
        "gender": "female",
        "name": "Hafsat"
    },
    {
        "ethnic_group": "hausa",
        "gender": "female",
        "name": "Bilkisu"
    },
    {
        "ethnic_group": "hausa",
        "gender": "female",
        "name": "Safiya"
    },
    {
        "ethnic_group": "hausa",
        "gender": "female",
        "name": "Zulei"
    },
    {
        "ethnic_group": "hausa",
        "gender": "female",
        "name": "Lami"
    },
    {
        "ethnic_group": "hausa",
        "gender": "female",
        "name": "Hadiza"
    },
    {
        "ethnic_group": "hausa",
        "gender": "female",
        "name": "Binta"
    },
    {
        "ethnic_group": "hausa",
        "gender": "female",
        "name": "Zuwaira"
    },
    {
        "ethnic_group": "hausa",
        "gender": "female",
        "name": "Zainab"
    }
]